winencrypt/__init__.py
winencrypt/__version__.py
winencrypt/main.py
winencrypt/types.py
winencrypt-0.1.0.dist-info/METADATA
winencrypt-0.1.0.dist-info/WHEEL
winencrypt-0.1.0.dist-info/entry_points.txt
winencrypt-0.1.0.dist-info/licenses/LICENSE
winencrypt-0.1.0.dist-info/RECORD
