Metadata-Version: 2.1
Name: winencrypt
Version: 0.1.0
Summary: Basic data encryption for Windows.
Project-URL: Changelog, https://github.com/newvicx/winencrypt/blob/master/CHANGELOG.md
Project-URL: Homepage, https://github.com/newvicx/winencrypt
Project-URL: Source, https://github.com/newvicx/winencrypt
Author-email: Chris Newville <chrisnewville1396@gmail.com>
License-Expression: MIT
License-File: LICENSE
Classifier: Development Status :: 4 - Beta
Classifier: Environment :: Win32 (MS Windows)
Classifier: Intended Audience :: Developers
Classifier: License :: OSI Approved :: BSD License
Classifier: Operating System :: Microsoft :: Windows
Classifier: Programming Language :: Python :: 3
Classifier: Programming Language :: Python :: 3 :: Only
Classifier: Programming Language :: Python :: 3.6
Classifier: Programming Language :: Python :: 3.7
Classifier: Programming Language :: Python :: 3.8
Classifier: Programming Language :: Python :: 3.9
Classifier: Programming Language :: Python :: 3.10
Classifier: Programming Language :: Python :: 3.11
Requires-Python: >=3.6
Requires-Dist: click
Requires-Dist: pydantic
Requires-Dist: pywin32
